pydragon/__init__.py
pydragon/dragon.py
pydragon/dragon_pb2.py
pydragon/dragon_pb2_grpc.py
pydragon/common/common_pb2.py
pydragon/common/common_pb2_grpc.py
pydragon/services/common/service_pb2.py
pydragon/services/common/service_pb2_grpc.py
pydragon-0.1.3.dist-info/DESCRIPTION.rst
pydragon-0.1.3.dist-info/METADATA
pydragon-0.1.3.dist-info/RECORD
pydragon-0.1.3.dist-info/WHEEL
pydragon-0.1.3.dist-info/metadata.json
pydragon-0.1.3.dist-info/top_level.txt
