Metadata-Version: 2.0
Name: pydragon
Version: 0.1.3
Summary: Python3 client for Dragon
Home-page: UNKNOWN
Author: Nafis Ahmed
Author-email: nafis@algomatrix.co
License: MIT
Platform: UNKNOWN
Requires-Dist: grpcio (==1.7.0)
